pdfnup.py
pdfnup3-1.0.0.data/scripts/pdfnup
pdfnup3-1.0.0.dist-info/LICENSE
pdfnup3-1.0.0.dist-info/METADATA
pdfnup3-1.0.0.dist-info/WHEEL
pdfnup3-1.0.0.dist-info/top_level.txt
pdfnup3-1.0.0.dist-info/RECORD
