Metadata-Version: 2.1
Name: pdfnup3
Version: 1.0.0
Summary: Layout multiple pages per sheet of a PDF document.
Home-page: http://www.dinu-gherman.net/
Author: Dinu Gherman
Author-email: gherman@darwin.in-berlin.de
Maintainer: Dinu Gherman
Maintainer-email: gherman@darwin.in-berlin.de
License: GPL 3
Download-URL: http://www.dinu-gherman.net/tmp/pdfnup-1.0.0.tar.gz
Keywords: PDF,minimizig pages
Platform: Posix
Platform: Windows
Classifier: Development Status :: 4 - Beta
Classifier: Environment :: Console
Classifier: Intended Audience :: End Users/Desktop
Classifier: Intended Audience :: Developers
Classifier: License :: OSI Approved :: GNU General Public License (GPL)
Classifier: Operating System :: MacOS :: MacOS X
Classifier: Operating System :: POSIX
Classifier: Operating System :: Microsoft :: Windows
Classifier: Programming Language :: Python
Classifier: Topic :: Utilities
Classifier: Topic :: Printing
Requires-Dist: PyPDF2
